{"metaData":{"resolution":0.5,"tempo":98,"pickups":0,"subsPerMeasure":6},"notes":[{"s":[{"value":"F/4","duration":"4"},{"value":"c/4","duration":"8r"},{"value":"F/4","duration":"4"},{"value":"c/4","duration":"8r"},{"value":"G/4","duration":"4"}],"a":[{"value":"C/4","duration":"4"},{"value":"c/4","duration":"8r"},{"value":"D/4","duration":"4"},{"value":"c/4","duration":"8r"},{"value":"D/4","duration":"4"}],"t":[{"value":"A/3","duration":"4"},{"value":"c/4","duration":"8r"},{"value":"A/3","duration":"4"},{"value":"c/4","duration":"8r"},{"value":"Bb/3","duration":"4"}],"b":[{"value":"F/3","duration":"4"},{"value":"c/4","duration":"8r"},{"value":"D/3","duration":"4"},{"value":"c/4","duration":"8r"},{"value":"Bb/2","duration":"4"}],"ts":[3,4],"lyrics":[[{"value":"My","duration":"4"},{"value":"country,","duration":"4"},{"value":"’tis","duration":"4"}],[{"value":"My","duration":"4"},{"value":"native","duration":"4"},{"value":"country,","duration":"4"}],[{"value":"Let","duration":"4"},{"value":"music","duration":"4"},{"value":"swell","duration":"4"}],[{"value":"Our","duration":"4"},{"value":"fathers’","duration":"4"},{"value":"God,","duration":"4"}]]},{"s":[{"value":"E/4","duration":"4d"},{"value":"F/4","duration":"8"},{"value":"G/4","duration":"4"}],"a":[{"value":"C/4","duration":"4d"},{"value":"D/4","duration":"8"},{"value":"E/4","duration":"4"}],"t":[{"value":"G/3","duration":"4d"},{"value":"C/4","duration":"8"},{"value":"C/4","duration":"4"}],"b":[{"value":"C/3","duration":"4d"},{"value":"C/3","duration":"8"},{"value":"C/3","duration":"4"}],"ts":[3,4],"lyrics":[[{"value":"of","duration":"4d"},{"value":"thee,","duration":"8"},{"value":"Sweet","duration":"4"}],[{"value":"thee,","duration":"4d"},{"value":"Land","duration":"8"},{"value":"of","duration":"4"}],[{"value":"the","duration":"4d"},{"value":"breeze,","duration":"8"},{"value":"And","duration":"4"}],[{"value":"to","duration":"4d"},{"value":"Thee,","duration":"8"},{"value":"Author","duration":"4"}]]},{"s":[{"value":"A/4","duration":"4"},{"value":"A/4","duration":"4"},{"value":"Bb/4","duration":"4"}],"a":[{"value":"F/4","duration":"4"},{"value":"F/4","duration":"4"},{"value":"G/4","duration":"4"}],"t":[{"value":"C/4","duration":"4"},{"value":"D/4","duration":"4"},{"value":"D/4","duration":"4"}],"b":[{"value":"F/3","duration":"4"},{"value":"D/3","duration":"4"},{"value":"Bb/2","duration":"4"}],"ts":[3,4],"lyrics":[[{"value":"land","duration":"4"},{"value":"of","duration":"4"},{"value":"liberty,","duration":"4"}],[{"value":"the","duration":"4"},{"value":"noble","duration":"4"},{"value":"free,","duration":"4"}],[{"value":"ring","duration":"4"},{"value":"from","duration":"4"},{"value":"all","duration":"4"}],[{"value":"of","duration":"4"},{"value":"liberty,","duration":"4"},{"value":"To","duration":"4"}]]},{"s":[{"value":"A/4","duration":"4d"},{"value":"G/4","duration":"8"},{"value":"F/4","duration":"4"}],"a":[{"value":"F/4","duration":"4d"},{"value":"E/4","duration":"8"},{"value":"F/4","duration":"4"}],"t":[{"value":"C/4","duration":"4d"},{"value":"Bb/3","duration":"8"},{"value":"A/3","duration":"4"}],"b":[{"value":"C/3","duration":"4d"},{"value":"C/3","duration":"8"},{"value":"D/3","duration":"4"}],"ts":[3,4],"lyrics":[[{"value":"Of","duration":"4d"},{"value":"thee","duration":"8"},{"value":"I","duration":"4"}],[{"value":"Thy","duration":"4d"},{"value":"name","duration":"8"},{"value":"I","duration":"4"}],[{"value":"the","duration":"4d"},{"value":"trees,","duration":"8"},{"value":"Sweet","duration":"4"}],[{"value":"Thee","duration":"4d"},{"value":"we","duration":"8"},{"value":"sing;","duration":"4"}]]},{"s":[{"value":"G/4","duration":"4"},{"value":"F/4","duration":"4"},{"value":"E/4","duration":"4"}],"a":[{"value":"D/4","duration":"4"},{"value":"C/4","duration":"4"},{"value":"C/4","duration":"4"}],"t":[{"value":"Bb/3","duration":"4"},{"value":"A/3","duration":"4"},{"value":"G/3","duration":"4"}],"b":[{"value":"Bb/2","duration":"4"},{"value":"C/3","duration":"4"},{"value":"C/3","duration":"4"}],"ts":[3,4],"lyrics":[[{"value":"sing;","duration":"4"},{"value":"Land","duration":"4"},{"value":"where","duration":"4"}],[{"value":"love;","duration":"4"},{"value":"I","duration":"4"},{"value":"love","duration":"4"}],[{"value":"freedom’s","duration":"4"},{"value":"song;","duration":"4"},{"value":"Let","duration":"4"}],[{"value":"Long","duration":"4"},{"value":"may","duration":"4"},{"value":"our","duration":"4"}]]},{"s":[{"value":"F/4","duration":"2d"}],"a":[{"value":"C/4","duration":"2d"}],"t":[{"value":"A/3","duration":"2d"}],"b":[{"value":"F/3","duration":"2d"}],"ts":[3,4],"lyrics":[[{"value":"my","duration":"2d"}],[{"value":"thy","duration":"2d"}],[{"value":"mortal","duration":"2d"}],[{"value":"land","duration":"2d"}]]},{"s":[{"value":"C/5","duration":"4"},{"value":"C/5","duration":"4"},{"value":"C/5","duration":"4"}],"a":[{"value":"A/4","duration":"4"},{"value":"A/4","duration":"4"},{"value":"A/4","duration":"4"}],"t":[{"value":"C/4","duration":"4"},{"value":"C/4","duration":"4"},{"value":"C/4","duration":"4"}],"b":[{"value":"F/3","duration":"4"},{"value":"A/3","duration":"4"},{"value":"C/4","duration":"4"}],"ts":[3,4],"lyrics":[[{"value":"fathers","duration":"4"},{"value":"died,","duration":"4"},{"value":"Land","duration":"4"}],[{"value":"rocks","duration":"4"},{"value":"and","duration":"4"},{"value":"rills,","duration":"4"}],[{"value":"tongues","duration":"4"},{"value":"awake;","duration":"4"},{"value":"Let","duration":"4"}],[{"value":"be","duration":"4"},{"value":"bright","duration":"4"},{"value":"With","duration":"4"}]]},{"s":[{"value":"C/5","duration":"4d"},{"value":"Bb/4","duration":"8"},{"value":"A/4","duration":"4"}],"a":[{"value":"A/4","duration":"4d"},{"value":"G/4","duration":"8"},{"value":"F/4","duration":"4"}],"t":[{"value":"C/4","duration":"4d"},{"value":"C/4","duration":"8"},{"value":"C/4","duration":"4"}],"b":[{"value":"F/3","duration":"4d"},{"value":"F/3","duration":"8"},{"value":"F/3","duration":"4"}],"ts":[3,4],"lyrics":[[{"value":"of","duration":"4d"},{"value":"the","duration":"8"},{"value":"pilgrims’","duration":"4"}],[{"value":"Thy","duration":"4d"},{"value":"woods","duration":"8"},{"value":"and","duration":"4"}],[{"value":"all","duration":"4d"},{"value":"that","duration":"8"},{"value":"breathe","duration":"4"}],[{"value":"freedom’s","duration":"4d"},{"value":"holy","duration":"8"},{"value":"light;","duration":"4"}]]},{"s":[{"value":"Bb/4","duration":"4"},{"value":"Bb/4","duration":"4"},{"value":"Bb/4","duration":"4"}],"a":[{"value":"G/4","duration":"4"},{"value":"G/4","duration":"4"},{"value":"G/4","duration":"4"}],"t":[{"value":"C/4","duration":"4"},{"value":"C/4","duration":"4"},{"value":"C/4","duration":"4"}],"b":[{"value":"C/3","duration":"4"},{"value":"E/3","duration":"4"},{"value":"G/3","duration":"4"}],"ts":[3,4],"lyrics":[[{"value":"pride,","duration":"4"},{"value":"From","duration":"4"},{"value":"every","duration":"4"}],[{"value":"templed","duration":"4"},{"value":"hills;","duration":"4"},{"value":"My","duration":"4"}],[{"value":"partake;","duration":"4"},{"value":"Let","duration":"4"},{"value":"rocks","duration":"4"}],[{"value":"Protect","duration":"4"},{"value":"us","duration":"4"},{"value":"by","duration":"4"}]]},{"s":[{"value":"Bb/4","duration":"4d"},{"value":"A/4","duration":"8"},{"value":"G/4","duration":"4"}],"a":[{"value":"G/4","duration":"4d"},{"value":"F/4","duration":"8"},{"value":"E/4","duration":"4"}],"t":[{"value":"C/4","duration":"4d"},{"value":"C/4","duration":"8"},{"value":"C/4","duration":"4"}],"b":[{"value":"C/3","duration":"4d"},{"value":"C/3","duration":"8"},{"value":"C/3","duration":"4"}],"ts":[3,4],"lyrics":[[{"value":"mountainside,","duration":"4d"},{"value":"Let","duration":"8"},{"value":"freedom","duration":"4"}],[{"value":"heart","duration":"4d"},{"value":"with","duration":"8"},{"value":"rapture","duration":"4"}],[{"value":"their","duration":"4d"},{"value":"silence","duration":"8"},{"value":"break,","duration":"4"}],[{"value":"Thy","duration":"4d"},{"value":"might,","duration":"8"},{"value":"Great","duration":"4"}]]},{"s":[{"value":"A/4","duration":"4"},{"value":"Bb/4","duration":"8"},{"value":"A/4","duration":"8"},{"value":"G/4","duration":"8"},{"value":"F/4","duration":"8"}],"a":[{"value":"F/4","duration":"4"},{"value":"F/4","duration":"4"},{"value":"C/4","duration":"4"}],"t":[{"value":"C/4","duration":"4"},{"value":"D/4","duration":"8"},{"value":"C/4","duration":"8"},{"value":"Bb/3","duration":"8"},{"value":"A/3","duration":"8"}],"b":[{"value":"F/3","duration":"4"},{"value":"F/3","duration":"4"},{"value":"F/3","duration":"4"}],"ts":[3,4],"lyrics":[[{"value":"ring!","duration":"4"}],[{"value":"thrills,","duration":"4"}],[{"value":"The","duration":"4"}],[{"value":"God,","duration":"4"}]]},{"s":[{"value":"A/4","duration":"4d"},{"value":"Bb/4","duration":"8"},{"value":"C/5","duration":"4"}],"a":[{"value":"F/4","duration":"4d"},{"value":"F/4","duration":"8"},{"value":"F/4","duration":"4"}],"t":[{"value":"C/4","duration":"4d"},{"value":"C/4","duration":"8"},{"value":"C/4","duration":"4"}],"b":[{"value":"F/3","duration":"4d"},{"value":"G/3","duration":"8"},{"value":"A/3","duration":"4"}],"ts":[3,4],"lyrics":[]},{"s":[{"value":"D/5","duration":"8"},{"value":"Bb/4","duration":"8"},{"value":"A/4","duration":"4"},{"value":"G/4","duration":"4"}],"a":[{"value":"F/4","duration":"8"},{"value":"G/4","duration":"8"},{"value":"F/4","duration":"4"},{"value":"E/4","duration":"4"}],"t":[{"value":"Bb/3","duration":"8"},{"value":"D/4","duration":"8"},{"value":"C/4","duration":"4"},{"value":"Bb/3","duration":"4"}],"b":[{"value":"Bb/3","duration":"4"},{"value":"C/4","duration":"4"},{"value":"C/3","duration":"4"}],"ts":[3,4],"lyrics":[]},{"s":[{"value":"F/4","duration":"2d"}],"a":[{"value":"F/4","duration":"2d"}],"t":[{"value":"A/3","duration":"2d"}],"b":[{"value":"F/3","duration":"2d"}],"ts":[3,4],"lyrics":[]}]}